{"mean":{"confidence_interval":{"confidence_level":0.95,"lower_bound":386410184.68775,"upper_bound":390745200.52524996},"point_estimate":388483447.47,"standard_error":1108353.6789957401},"median":{"confidence_interval":{"confidence_level":0.95,"lower_bound":382290625.0,"upper_bound":386063854.5},"point_estimate":383866854.0,"standard_error":979398.5089484117},"median_abs_dev":{"confidence_interval":{"confidence_level":0.95,"lower_bound":3317625.8219003677,"upper_bound":8555640.149952013},"point_estimate":5346224.370485544,"standard_error":1406325.1493822543},"slope":null,"std_dev":{"confidence_interval":{"confidence_level":0.95,"lower_bound":8615566.516809713,"upper_bound":13586247.02297409},"point_estimate":11133209.455985153,"standard_error":1277576.3260195605}}